{
  "Urnula craterium": {
    "edibility": "Unknown",
    "notes": "Devils urn. Black urn-shaped cup. Inedible."
  },
  "Leccinum albostipitatum": {
    "edibility": "Edible",
    "notes": "Widely recognized as edible. Always cook thoroughly and verify with an expert."
  },
  "Lactarius deliciosus": {
    "edibility": "Edible",
    "notes": "Saffron milkcap. Orange cap, green staining, grows with pine. Edible."
  },
  "Clitocybe nebularis": {
    "edibility": "Unknown",
    "notes": "Clouded funnel. Grey-brown funnel cap. Edible but some report GI issues."
  },
  "Hypholoma fasciculare": {
    "edibility": "Poisonous",
    "notes": "Sulphur tuft. Clustered on stumps, greenish gills. Poisonous."
  },
  "Lactarius torminosus": {
    "edibility": "Poisonous",
    "notes": "Woolly milkcap. Pinkish woolly cap, very hot/peppery. Poisonous."
  },
  "Lycoperdon perlatum": {
    "edibility": "Edible",
    "notes": "Common puffball. Round with spines, white inside when young. Edible."
  },
  "Verpa bohemica": {
    "edibility": "Poisonous",
    "notes": "Early morel. Thimble-shaped cap. Poisonous raw, risky even cooked."
  },
  "Schizophyllum commune": {
    "edibility": "Unknown",
    "notes": "Splitgill. Small fan-shaped with split gills. Inedible."
  },
  "Leccinum aurantiacum": {
    "edibility": "Edible",
    "notes": "Widely recognized as edible. Always cook thoroughly and verify with an expert."
  },
  "Phellinus igniarius": {
    "edibility": "Unknown",
    "notes": "Cramp balls. Black hard bracket. Inedible."
  },
  "Suillus luteus": {
    "edibility": "Edible",
    "notes": "Slippery jack. Slimy brown cap, purple pores. Edible, peel skin first."
  },
  "Coltricia perennis": {
    "edibility": "Unknown",
    "notes": "Edibility unknown or unverified. Do not consume without positive identification by a certified mycologist."
  },
  "Cetraria islandica": {
    "edibility": "Unknown",
    "notes": "Iceland moss. Fruticose lichen. Lichen, not a mushroom."
  },
  "Amanita muscaria": {
    "edibility": "Poisonous",
    "notes": "Fly agaric. Bright red cap with white spots. Contains muscimol. Poisonous."
  },
  "Pholiota aurivella": {
    "edibility": "Edible",
    "notes": "Golden pholiota. Scaly golden cap on wood. Edible."
  },
  "Trichaptum biforme": {
    "edibility": "Unknown",
    "notes": "Violet-toothed polypore. Violet spines underneath. Inedible."
  },
  "Artomyces pyxidatus": {
    "edibility": "Edible",
    "notes": "Crown-tipped coral. White coral with crown tips. Edible."
  },
  "Calocera viscosa": {
    "edibility": "Unknown",
    "notes": "Yellow stagshorn. Jelly fungus, antler-like. Inedible."
  },
  "Sarcosoma globosum": {
    "edibility": "Unknown",
    "notes": "Black bulgar. Black jelly-like blobs. Inedible."
  },
  "Evernia prunastri": {
    "edibility": "Unknown",
    "notes": "Oakmoss. Fruticose lichen. Lichen, not a mushroom."
  },
  "Laetiporus sulphureus": {
    "edibility": "Edible",
    "notes": "Chicken of the woods. Bright orange-yellow shelves on wood. Excellent edible."
  },
  "Lobaria pulmonaria": {
    "edibility": "Unknown",
    "notes": "Edibility unknown or unverified. Do not consume without positive identification by a certified mycologist."
  },
  "Bjerkandera adusta": {
    "edibility": "Unknown",
    "notes": "Smoky polypore. Smoky grey bracket. Inedible."
  },
  "Vulpicida pinastri": {
    "edibility": "Unknown",
    "notes": "Powdered sunshine lichen. Yellow-green lichen. Lichen, not a mushroom."
  },
  "Imleria badia": {
    "edibility": "Edible",
    "notes": "Bay bolete. Chestnut cap, yellow pores bruise blue-green. Excellent edible."
  },
  "Evernia mesomorpha": {
    "edibility": "Unknown",
    "notes": "Boreal oakmoss. Fruticose lichen. Lichen, not a mushroom."
  },
  "Physcia adscendens": {
    "edibility": "Unknown",
    "notes": "Hooded rosette lichen. Foliose lichen. Lichen, not a mushroom."
  },
  "Coprinellus micaceus": {
    "edibility": "Unknown",
    "notes": "Edibility unknown or unverified. Do not consume without positive identification by a certified mycologist."
  },
  "Armillaria borealis": {
    "edibility": "Edible",
    "notes": "Honey fungus. Clustered on wood, honey-colored cap. Edible when cooked thoroughly."
  },
  "Trametes ochracea": {
    "edibility": "Unknown",
    "notes": "Ochre bracket. Similar to turkey tail. Inedible."
  },
  "Cantharellus cibarius": {
    "edibility": "Edible",
    "notes": "Golden chanterelle. Bright yellow, forked gills running down stem, apricot smell. Excellent edible."
  },
  "Pseudevernia furfuracea": {
    "edibility": "Unknown",
    "notes": "Oakmoss lichen. Fruticose lichen. Lichen, not a mushroom."
  },
  "Tremella mesenterica": {
    "edibility": "Unknown",
    "notes": "Witchs butter. Yellow jelly fungus. Inedible."
  },
  "Gyromitra infula": {
    "edibility": "Poisonous",
    "notes": "Hooded false morel. Saddle-shaped. Poisonous."
  },
  "Leccinum versipelle": {
    "edibility": "Edible",
    "notes": "Widely recognized as edible. Always cook thoroughly and verify with an expert."
  },
  "Mutinus ravenelii": {
    "edibility": "Unknown",
    "notes": "Dog stinkhorn. Reddish phallic shape. Inedible."
  },
  "Pholiota squarrosa": {
    "edibility": "Edible",
    "notes": "Shaggy scalycap. Scaly cap on wood. Edible."
  },
  "Amanita rubescens": {
    "edibility": "Edible",
    "notes": "Blusher. Pinkish cap, flesh bruises reddish. Edible when cooked thoroughly."
  },
  "Amanita pantherina": {
    "edibility": "Poisonous",
    "notes": "Panther cap. Brown cap with white warts. Contains muscimol. Poisonous."
  },
  "Sarcoscypha austriaca": {
    "edibility": "Unknown",
    "notes": "Scarlet elfcup. Bright red cup on wood. Inedible."
  },
  "Boletus edulis": {
    "edibility": "Edible",
    "notes": "King bolete / porcini. Brown cap, white pores, bulbous stem. Highly prized edible."
  },
  "Coprinus comatus": {
    "edibility": "Edible",
    "notes": "Shaggy ink cap. Tall white shaggy cap, auto-digests into black ink. Edible when young."
  },
  "Merulius tremellosus": {
    "edibility": "Unknown",
    "notes": "Jelly rot. Translucent jelly fungus. Inedible."
  },
  "Stropharia aeruginosa": {
    "edibility": "Poisonous",
    "notes": "Verdigris agaric. Blue-green cap. Poisonous."
  },
  "Cladonia fimbriata": {
    "edibility": "Unknown",
    "notes": "Trumpet lichen. Cup lichen. Lichen, not a mushroom."
  },
  "Suillus grevillei": {
    "edibility": "Edible",
    "notes": "Larch bolete. Orange-yellow cap with larch. Edible."
  },
  "Apioperdon pyriforme": {
    "edibility": "Edible",
    "notes": "Pear-shaped puffball. Grows on wood, white inside. Edible."
  },
  "Cerioporus squamosus": {
    "edibility": "Edible",
    "notes": "Dryads saddle. Scaly bracket on wood. Edible when young."
  },
  "Leccinum scabrum": {
    "edibility": "Edible",
    "notes": "Birch bolete. Brown cap, tall stem with black scabers. Edible."
  },
  "Rhytisma acerinum": {
    "edibility": "Unknown",
    "notes": "Tar spot. Black spots on maple leaves. Not a mushroom — fungus on leaves."
  },
  "Hypholoma lateritium": {
    "edibility": "Poisonous",
    "notes": "Brick cap. Reddish cap, clustered on wood. Poisonous."
  },
  "Flammulina velutipes": {
    "edibility": "Edible",
    "notes": "Velvet shank. Dark velvety stem, orange cap. Edible."
  },
  "Tricholomopsis rutilans": {
    "edibility": "Unknown",
    "notes": "Plums and custard. Purple-brown scaly cap on conifer wood. Inedible."
  },
  "Coprinopsis atramentaria": {
    "edibility": "Poisonous",
    "notes": "Common ink cap. Grey-brown cap. Poisonous with alcohol (disulfiram reaction)."
  },
  "Trametes versicolor": {
    "edibility": "Unknown",
    "notes": "Turkey tail. Colorful bracket with concentric zones. Inedible (too tough)."
  },
  "Graphis scripta": {
    "edibility": "Unknown",
    "notes": "Script lichen. Script-like marks on bark. Lichen, not a mushroom."
  },
  "Ganoderma applanatum": {
    "edibility": "Unknown",
    "notes": "Artists conk. Large white bracket. Inedible."
  },
  "Phellinus tremulae": {
    "edibility": "Unknown",
    "notes": "Aspen bracket. Hard bracket on aspen. Inedible."
  },
  "Peltigera aphthosa": {
    "edibility": "Unknown",
    "notes": "Green dog lichen. Foliose lichen. Lichen, not a mushroom."
  },
  "Parmelia sulcata": {
    "edibility": "Unknown",
    "notes": "Hammered shield lichen. Grey-green foliose lichen. Lichen, not a mushroom."
  },
  "Fomitopsis betulina": {
    "edibility": "Unknown",
    "notes": "Birch polypore. White bracket on birch. Inedible."
  },
  "Pleurotus pulmonarius": {
    "edibility": "Edible",
    "notes": "Phoenix oyster. Pale, shell-like cap on wood. Edible."
  },
  "Fomitopsis pinicola": {
    "edibility": "Unknown",
    "notes": "Red-belted conk. Red-banded bracket. Inedible."
  },
  "Daedaleopsis confragosa": {
    "edibility": "Unknown",
    "notes": "Thin-walled maze polypore. Bracket with maze-like pores. Inedible."
  },
  "Hericium coralloides": {
    "edibility": "Edible",
    "notes": "Coral tooth. White coral-like fruit body on hardwood. Edible."
  },
  "Trametes hirsuta": {
    "edibility": "Unknown",
    "notes": "Hairy bracket. White to grey bracket. Inedible."
  },
  "Coprinellus disseminatus": {
    "edibility": "Unknown",
    "notes": "Edibility unknown or unverified. Do not consume without positive identification by a certified mycologist."
  },
  "Kuehneromyces mutabilis": {
    "edibility": "Poisonous",
    "notes": "Sheathed woodtuft. Two-toned cap. Poisonous — confused with honey fungus."
  },
  "Pleurotus ostreatus": {
    "edibility": "Edible",
    "notes": "Oyster mushroom. Shelf-like on wood, decurrent gills. Edible and cultivated."
  },
  "Phlebia radiata": {
    "edibility": "Unknown",
    "notes": "Crimped gill. Wrinkled orange crust. Inedible."
  },
  "Boletus reticulatus": {
    "edibility": "Edible",
    "notes": "Summer bolete. Net-like pattern on stem. Excellent edible."
  },
  "Phallus impudicus": {
    "edibility": "Unknown",
    "notes": "Stinkhorn. Phallic shape, foul smell. Inedible (egg stage eaten in some cultures)."
  },
  "Macrolepiota procera": {
    "edibility": "Edible",
    "notes": "Parasol mushroom. Tall with scaly cap and snakeskin-patterned stem. Excellent edible."
  },
  "Fomes fomentarius": {
    "edibility": "Unknown",
    "notes": "Tinder fungus. Hoof-shaped bracket. Inedible."
  },
  "Suillus granulatus": {
    "edibility": "Edible",
    "notes": "Granulated bolete. No ring, milky droplets on pores. Edible."
  },
  "Gyromitra esculenta": {
    "edibility": "Poisonous",
    "notes": "False morel. Brain-like, reddish-brown. Contains gyromitrin — potentially FATAL."
  },
  "Xanthoria parietina": {
    "edibility": "Unknown",
    "notes": "Common orange lichen. Bright orange lichen. Lichen, not a mushroom."
  },
  "Nectria cinnabarina": {
    "edibility": "Unknown",
    "notes": "Coral spot. Small red spots on dead wood. Inedible."
  },
  "Sarcomyxa serotina": {
    "edibility": "Edible",
    "notes": "Late oyster. Olive-yellow gills on wood. Edible."
  },
  "Inonotus obliquus": {
    "edibility": "Unknown",
    "notes": "Chaga. Black burnt-looking growth on birch. Inedible as food."
  },
  "Panellus stipticus": {
    "edibility": "Unknown",
    "notes": "Bitter oyster. Small bracket, bioluminescent. Inedible."
  },
  "Hypogymnia physodes": {
    "edibility": "Unknown",
    "notes": "Puffed lichen. Grey-green foliose lichen. Lichen, not a mushroom."
  },
  "Hygrophoropsis aurantiaca": {
    "edibility": "Poisonous",
    "notes": "False chanterelle. Orange, thinner gills, grows on wood. Poisonous."
  },
  "Cladonia rangiferina": {
    "edibility": "Unknown",
    "notes": "Reindeer lichen. Fruticose lichen. Lichen, not a mushroom."
  },
  "Platismatia glauca": {
    "edibility": "Unknown",
    "notes": "Ruffled lichen. Grey-green foliose lichen. Lichen, not a mushroom."
  },
  "Calycina citrina": {
    "edibility": "Unknown",
    "notes": "Lemon discos. Tiny yellow cups. Inedible."
  },
  "Cladonia stellaris": {
    "edibility": "Unknown",
    "notes": "Star-tipped reindeer lichen. Fruticose lichen. Lichen, not a mushroom."
  },
  "Amanita citrina": {
    "edibility": "Poisonous",
    "notes": "False death cap. Yellowish cap, volva at base. Poisonous."
  },
  "Lepista nuda": {
    "edibility": "Edible",
    "notes": "Wood blewit. Purple-brown cap. Edible."
  },
  "Gyromitra gigas": {
    "edibility": "Poisonous",
    "notes": "Snow morel. Large brain-like cap. Poisonous."
  },
  "Crucibulum laeve": {
    "edibility": "Unknown",
    "notes": "Common birds nest. Small cups with egg-like peridioles. Inedible."
  },
  "Daedaleopsis tricolor": {
    "edibility": "Unknown",
    "notes": "Multicolor gill polypore. Bracket with gill-like pores. Inedible."
  },
  "Stereum hirsutum": {
    "edibility": "Unknown",
    "notes": "Hairy curtain crust. Thin bracket with hairy upper side. Inedible."
  },
  "Paxillus involutus": {
    "edibility": "Poisonous",
    "notes": "Brown roll-rim. Inrolled cap margin. Poisonous — can cause immune reaction."
  },
  "Lactarius turpis": {
    "edibility": "Poisonous",
    "notes": "Ugly milkcap. Dark olive-brown cap. Poisonous."
  },
  "Chlorociboria aeruginascens": {
    "edibility": "Unknown",
    "notes": "Green elfcup. Tiny turquoise cup fungus. Inedible."
  },
  "Chondrostereum purpureum": {
    "edibility": "Unknown",
    "notes": "Silverleaf fungus. Violet crust on wood. Inedible."
  },
  "Phaeophyscia orbicularis": {
    "edibility": "Unknown",
    "notes": "Shadow lichen. Grey foliose lichen. Lichen, not a mushroom."
  },
  "Peltigera praetextata": {
    "edibility": "Unknown",
    "notes": "Scaly dog lichen. Foliose lichen. Lichen, not a mushroom."
  },
  "Agaricus essettei": {
    "edibility": "Unknown",
    "notes": "Edibility unknown or unverified. Do not consume without positive identification by a certified mycologist."
  },
  "Clitocybe nitrophila": {
    "edibility": "Unknown",
    "notes": "Nitrophilous clitocybe. Small greyish cap on nutrient-rich soils. Edibility unknown or unverified. Do not consume."
  },
  "Infundibulicybe costata": {
    "edibility": "Unknown",
    "notes": "Ribbed funnel cap. Funnel-shaped cap with ribbed stem. Edibility unknown or unverified. Do not consume."
  },
  "Mycena pelliculosa": {
    "edibility": "Unknown",
    "notes": "Small bonnet with a pelliculose cap surface. Edibility unknown or unverified. Do not consume."
  },
  "Russula globispora": {
    "edibility": "Unknown",
    "notes": "Globose-spored russula. Brittle gilled mushroom. Edibility unknown or unverified. Do not consume."
  },
  "Russula lepida": {
    "edibility": "Unknown",
    "notes": "Pretty russula. Pink to purple cap. Edibility unknown or unverified. Do not consume."
  },
  "Russula mairei": {
    "edibility": "Unknown",
    "notes": "Maire's russula. Brittle gilled mushroom. Edibility unknown or unverified. Do not consume."
  },
  "Russula nigricans": {
    "edibility": "Unknown",
    "notes": "Blackening brittlegill. Flesh bruises black. Edibility unknown or unverified. Do not consume."
  },
  "Russula undulata": {
    "edibility": "Unknown",
    "notes": "Wavy russula. Undulating cap margin. Edibility unknown or unverified. Do not consume."
  },
  "Russula velutipes": {
    "edibility": "Unknown",
    "notes": "Velvet-footed russula. Velvety stem surface. Edibility unknown or unverified. Do not consume."
  },
  "Singerocybe phaeophthalma": {
    "edibility": "Unknown",
    "notes": "Pearly powdercap. Small grey-brown cap. Edibility unknown or unverified. Do not consume."
  }
}